[
    {"text": "Week #1: October 19th - October 25th, 2025", "done": true},
    {"text": "Week #2: October 26th - November 1st, 2025", "done": true},
    {"text": "Week #3: November 2nd - November 8th, 2025", "done": true},
    {"text": "Week #4: November 9th - November 15th, 2025", "done": true},
    {"text": "Week #5: November 16th - November 22nd, 2025", "done": true},
    {"text": "Week #6: November 23rd - November 29th, 2025", "done": true},
    {"text": "Week #7: November 30th - December 6th, 2025", "done": true},
    {"text": "Week #8: December 7th - December 13th, 2025", "done": true},
    {"text": "Week #9: December 14th - December 20th, 2025", "done": false}
]